[
  {
    "temperature": 24.21,
    "humidity": 34.52,
    "pressure": 1001.86,
    "gas": 123175,
    "altitude": 95.23,
    "timestamp": "2025-11-06T03:27:09.646788Z"
  },
  {
    "temperature": 24.2,
    "humidity": 34.59,
    "pressure": 1001.86,
    "gas": 49802,
    "altitude": 95.29,
    "timestamp": "2025-11-06T03:27:21.054138Z"
  },
  {
    "temperature": 24.2,
    "humidity": 34.6,
    "pressure": 1001.86,
    "gas": 56130,
    "altitude": 95.27,
    "timestamp": "2025-11-06T03:27:32.476117Z"
  },
  {
    "temperature": 24.19,
    "humidity": 34.62,
    "pressure": 1001.85,
    "gas": 57312,
    "altitude": 95.33,
    "timestamp": "2025-11-06T03:27:43.944915Z"
  },
  {
    "temperature": 24.16,
    "humidity": 34.61,
    "pressure": 1001.85,
    "gas": 104295,
    "altitude": 95.37,
    "timestamp": "2025-11-06T03:27:52.997682Z"
  },
  {
    "temperature": 24.16,
    "humidity": 34.6,
    "pressure": 1001.85,
    "gas": 52465,
    "altitude": 95.37,
    "timestamp": "2025-11-06T03:27:55.451947Z"
  },
  {
    "temperature": 24.16,
    "humidity": 34.62,
    "pressure": 1001.85,
    "gas": 59037,
    "altitude": 95.32,
    "timestamp": "2025-11-06T03:28:04.463774Z"
  }
]